client/__init__.py
client/client_.py
client/clients/__init__.py
client/clients/add_contact.py
client/clients/client_db.py
client/clients/del_contact.py
client/clients/main.py
client/clients/main_conv.py
client/clients/start_dialog.py
client/clients/transport.py
client/common/__init__.py
client/common/decos.py
client/common/descripts.py
client/common/errors.py
client/common/jim.py
client/common/metaclasses.py
client/common/utils.py
client/common/variables.py
client/logs/__init__.py
client/logs/client_log_config.py
client/logs/server_log_config.py
client/tests/__init__.py
client/tests/test_client.py
client/tests/test_jim.py
client/tests/test_server.py
client_pack_2try_version-0.8.7.dist-info/METADATA
client_pack_2try_version-0.8.7.dist-info/WHEEL
client_pack_2try_version-0.8.7.dist-info/top_level.txt
client_pack_2try_version-0.8.7.dist-info/RECORD
